{
  "directed": false,
  "multigraph": false,
  "graph": {},
  "nodes": [
    {
      "label": "apply_stories.py",
      "file_type": "code",
      "source_file": "apply_stories.py",
      "source_location": "L1",
      "_origin": "ast",
      "id": "apply_stories",
      "community": 19,
      "norm_label": "apply_stories.py"
    },
    {
      "label": "eslint.config.mjs",
      "file_type": "code",
      "source_file": "eslint.config.mjs",
      "source_location": "L1",
      "_origin": "ast",
      "id": "eslint_config",
      "community": 12,
      "norm_label": "eslint.config.mjs"
    },
    {
      "label": "eslintConfig",
      "file_type": "code",
      "source_file": "eslint.config.mjs",
      "source_location": "L5",
      "_origin": "ast",
      "id": "eslint_config_eslintconfig",
      "community": 12,
      "norm_label": "eslintconfig"
    },
    {
      "label": "extract.py",
      "file_type": "code",
      "source_file": "extract.py",
      "source_location": "L1",
      "_origin": "ast",
      "id": "extract",
      "community": 20,
      "norm_label": "extract.py"
    },
    {
      "label": "jules_automator.py",
      "file_type": "code",
      "source_file": "jules_automator.py",
      "source_location": "L1",
      "_origin": "ast",
      "id": "jules_automator",
      "community": 18,
      "norm_label": "jules_automator.py"
    },
    {
      "label": "run_applescript()",
      "file_type": "code",
      "source_file": "jules_automator.py",
      "source_location": "L32",
      "_origin": "ast",
      "id": "jules_automator_run_applescript",
      "community": 18,
      "norm_label": "run_applescript()"
    },
    {
      "label": "get_page_text()",
      "file_type": "code",
      "source_file": "jules_automator.py",
      "source_location": "L64",
      "_origin": "ast",
      "id": "jules_automator_get_page_text",
      "community": 18,
      "norm_label": "get_page_text()"
    },
    {
      "label": "next-env.d.ts",
      "file_type": "code",
      "source_file": "next-env.d.ts",
      "source_location": "L1",
      "_origin": "ast",
      "id": "next_env_d",
      "community": 17,
      "norm_label": "next-env.d.ts"
    },
    {
      "label": "next.config.ts",
      "file_type": "code",
      "source_file": "next.config.ts",
      "source_location": "L1",
      "_origin": "ast",
      "id": "next_config",
      "community": 13,
      "norm_label": "next.config.ts"
    },
    {
      "label": "nextConfig",
      "file_type": "code",
      "source_file": "next.config.ts",
      "source_location": "L3",
      "_origin": "ast",
      "id": "next_config_nextconfig",
      "community": 13,
      "norm_label": "nextconfig"
    },
    {
      "label": "postcss.config.mjs",
      "file_type": "code",
      "source_file": "postcss.config.mjs",
      "source_location": "L1",
      "_origin": "ast",
      "id": "postcss_config",
      "community": 15,
      "norm_label": "postcss.config.mjs"
    },
    {
      "label": "config",
      "file_type": "code",
      "source_file": "postcss.config.mjs",
      "source_location": "L1",
      "_origin": "ast",
      "id": "postcss_config_config",
      "community": 15,
      "norm_label": "config"
    },
    {
      "label": "page.tsx",
      "file_type": "code",
      "source_file": "src/app/about/page.tsx",
      "source_location": "L1",
      "_origin": "ast",
      "id": "about_page",
      "community": 9,
      "norm_label": "page.tsx"
    },
    {
      "label": "PixieDust()",
      "file_type": "code",
      "source_file": "src/app/about/page.tsx",
      "source_location": "L6",
      "_origin": "ast",
      "id": "about_page_pixiedust",
      "community": 9,
      "norm_label": "pixiedust()"
    },
    {
      "label": "About()",
      "file_type": "code",
      "source_file": "src/app/about/page.tsx",
      "source_location": "L53",
      "_origin": "ast",
      "id": "about_page_about",
      "community": 9,
      "norm_label": "about()"
    },
    {
      "label": "page.tsx",
      "file_type": "code",
      "source_file": "src/app/contact/page.tsx",
      "source_location": "L1",
      "_origin": "ast",
      "id": "contact_page",
      "community": 6,
      "norm_label": "page.tsx"
    },
    {
      "label": "GithubIcon()",
      "file_type": "code",
      "source_file": "src/app/contact/page.tsx",
      "source_location": "L5",
      "_origin": "ast",
      "id": "contact_page_githubicon",
      "community": 6,
      "norm_label": "githubicon()"
    },
    {
      "label": "LinkedinIcon()",
      "file_type": "code",
      "source_file": "src/app/contact/page.tsx",
      "source_location": "L12",
      "_origin": "ast",
      "id": "contact_page_linkedinicon",
      "community": 6,
      "norm_label": "linkedinicon()"
    },
    {
      "label": "Contact()",
      "file_type": "code",
      "source_file": "src/app/contact/page.tsx",
      "source_location": "L20",
      "_origin": "ast",
      "id": "contact_page_contact",
      "community": 6,
      "norm_label": "contact()"
    },
    {
      "label": "page.tsx",
      "file_type": "code",
      "source_file": "src/app/hobbies/page.tsx",
      "source_location": "L1",
      "_origin": "ast",
      "id": "hobbies_page",
      "community": 10,
      "norm_label": "page.tsx"
    },
    {
      "label": "hobbies",
      "file_type": "code",
      "source_file": "src/app/hobbies/page.tsx",
      "source_location": "L8",
      "_origin": "ast",
      "id": "hobbies_page_hobbies",
      "community": 10,
      "norm_label": "hobbies"
    },
    {
      "label": "HobbiesPage()",
      "file_type": "code",
      "source_file": "src/app/hobbies/page.tsx",
      "source_location": "L29",
      "_origin": "ast",
      "id": "hobbies_page_hobbiespage",
      "community": 10,
      "norm_label": "hobbiespage()"
    },
    {
      "label": "page.tsx",
      "file_type": "code",
      "source_file": "src/app/hobbies/photography/page.tsx",
      "source_location": "L1",
      "_origin": "ast",
      "id": "photography_page",
      "community": 7,
      "norm_label": "page.tsx"
    },
    {
      "label": "photos",
      "file_type": "code",
      "source_file": "src/app/hobbies/photography/page.tsx",
      "source_location": "L9",
      "_origin": "ast",
      "id": "photography_page_photos",
      "community": 7,
      "norm_label": "photos"
    },
    {
      "label": "PhotographyGallery()",
      "file_type": "code",
      "source_file": "src/app/hobbies/photography/page.tsx",
      "source_location": "L25",
      "_origin": "ast",
      "id": "photography_page_photographygallery",
      "community": 7,
      "norm_label": "photographygallery()"
    },
    {
      "label": "PhotoSection()",
      "file_type": "code",
      "source_file": "src/app/hobbies/photography/page.tsx",
      "source_location": "L86",
      "_origin": "ast",
      "id": "photography_page_photosection",
      "community": 7,
      "norm_label": "photosection()"
    },
    {
      "label": "page.tsx",
      "file_type": "code",
      "source_file": "src/app/lab/[slug]/page.tsx",
      "source_location": "L1",
      "_origin": "ast",
      "id": "src_app_lab_slug_page_tsx_slug_page",
      "community": 0,
      "norm_label": "page.tsx"
    },
    {
      "label": "ExperiencePage()",
      "file_type": "code",
      "source_file": "src/app/lab/[slug]/page.tsx",
      "source_location": "L10",
      "_origin": "ast",
      "id": "slug_page_experiencepage",
      "community": 0,
      "norm_label": "experiencepage()"
    },
    {
      "label": "page.tsx",
      "file_type": "code",
      "source_file": "src/app/lab/page.tsx",
      "source_location": "L1",
      "_origin": "ast",
      "id": "lab_page",
      "community": 0,
      "norm_label": "page.tsx"
    },
    {
      "label": "LabPage()",
      "file_type": "code",
      "source_file": "src/app/lab/page.tsx",
      "source_location": "L8",
      "_origin": "ast",
      "id": "lab_page_labpage",
      "community": 0,
      "norm_label": "labpage()"
    },
    {
      "label": "layout.tsx",
      "file_type": "code",
      "source_file": "src/app/layout.tsx",
      "source_location": "L1",
      "_origin": "ast",
      "id": "app_layout",
      "community": 1,
      "norm_label": "layout.tsx"
    },
    {
      "label": "metadata",
      "file_type": "code",
      "source_file": "src/app/layout.tsx",
      "source_location": "L9",
      "_origin": "ast",
      "id": "app_layout_metadata",
      "community": 1,
      "norm_label": "metadata"
    },
    {
      "label": "RootLayout()",
      "file_type": "code",
      "source_file": "src/app/layout.tsx",
      "source_location": "L37",
      "_origin": "ast",
      "id": "app_layout_rootlayout",
      "community": 1,
      "norm_label": "rootlayout()"
    },
    {
      "label": "page.tsx",
      "file_type": "code",
      "source_file": "src/app/now/page.tsx",
      "source_location": "L1",
      "_origin": "ast",
      "id": "now_page",
      "community": 14,
      "norm_label": "page.tsx"
    },
    {
      "label": "Now()",
      "file_type": "code",
      "source_file": "src/app/now/page.tsx",
      "source_location": "L1",
      "_origin": "ast",
      "id": "now_page_now",
      "community": 14,
      "norm_label": "now()"
    },
    {
      "label": "page.tsx",
      "file_type": "code",
      "source_file": "src/app/page.tsx",
      "source_location": "L1",
      "_origin": "ast",
      "id": "app_page",
      "community": 5,
      "norm_label": "page.tsx"
    },
    {
      "label": "Home()",
      "file_type": "code",
      "source_file": "src/app/page.tsx",
      "source_location": "L9",
      "_origin": "ast",
      "id": "app_page_home",
      "community": 5,
      "norm_label": "home()"
    },
    {
      "label": "page.tsx",
      "file_type": "code",
      "source_file": "src/app/project/[slug]/page.tsx",
      "source_location": "L1",
      "_origin": "ast",
      "id": "src_app_project_slug_page_tsx_slug_page",
      "community": 0,
      "norm_label": "page.tsx"
    },
    {
      "label": "getTheme()",
      "file_type": "code",
      "source_file": "src/app/project/[slug]/page.tsx",
      "source_location": "L12",
      "_origin": "ast",
      "id": "slug_page_gettheme",
      "community": 0,
      "norm_label": "gettheme()"
    },
    {
      "label": "ProjectPage()",
      "file_type": "code",
      "source_file": "src/app/project/[slug]/page.tsx",
      "source_location": "L23",
      "_origin": "ast",
      "id": "slug_page_projectpage",
      "community": 0,
      "norm_label": "projectpage()"
    },
    {
      "label": "page.tsx",
      "file_type": "code",
      "source_file": "src/app/projects/page.tsx",
      "source_location": "L1",
      "_origin": "ast",
      "id": "projects_page",
      "community": 4,
      "norm_label": "page.tsx"
    },
    {
      "label": "allCategories",
      "file_type": "code",
      "source_file": "src/app/projects/page.tsx",
      "source_location": "L9",
      "_origin": "ast",
      "id": "projects_page_allcategories",
      "community": 4,
      "norm_label": "allcategories"
    },
    {
      "label": "getTheme()",
      "file_type": "code",
      "source_file": "src/app/projects/page.tsx",
      "source_location": "L11",
      "_origin": "ast",
      "id": "projects_page_gettheme",
      "community": 4,
      "norm_label": "gettheme()"
    },
    {
      "label": "ProjectCard()",
      "file_type": "code",
      "source_file": "src/app/projects/page.tsx",
      "source_location": "L18",
      "_origin": "ast",
      "id": "projects_page_projectcard",
      "community": 4,
      "norm_label": "projectcard()"
    },
    {
      "label": "Projects()",
      "file_type": "code",
      "source_file": "src/app/projects/page.tsx",
      "source_location": "L49",
      "_origin": "ast",
      "id": "projects_page_projects",
      "community": 4,
      "norm_label": "projects()"
    },
    {
      "label": "page.tsx",
      "file_type": "code",
      "source_file": "src/app/skills/page.tsx",
      "source_location": "L1",
      "_origin": "ast",
      "id": "skills_page",
      "community": 11,
      "norm_label": "page.tsx"
    },
    {
      "label": "skillCategories",
      "file_type": "code",
      "source_file": "src/app/skills/page.tsx",
      "source_location": "L6",
      "_origin": "ast",
      "id": "skills_page_skillcategories",
      "community": 11,
      "norm_label": "skillcategories"
    },
    {
      "label": "Skills()",
      "file_type": "code",
      "source_file": "src/app/skills/page.tsx",
      "source_location": "L25",
      "_origin": "ast",
      "id": "skills_page_skills",
      "community": 11,
      "norm_label": "skills()"
    },
    {
      "label": "page.tsx",
      "file_type": "code",
      "source_file": "src/app/timeline/page.tsx",
      "source_location": "L1",
      "_origin": "ast",
      "id": "timeline_page",
      "community": 8,
      "norm_label": "page.tsx"
    },
    {
      "label": "timelineEvents",
      "file_type": "code",
      "source_file": "src/app/timeline/page.tsx",
      "source_location": "L6",
      "_origin": "ast",
      "id": "timeline_page_timelineevents",
      "community": 8,
      "norm_label": "timelineevents"
    },
    {
      "label": "getTheme()",
      "file_type": "code",
      "source_file": "src/app/timeline/page.tsx",
      "source_location": "L35",
      "_origin": "ast",
      "id": "timeline_page_gettheme",
      "community": 8,
      "norm_label": "gettheme()"
    },
    {
      "label": "Timeline()",
      "file_type": "code",
      "source_file": "src/app/timeline/page.tsx",
      "source_location": "L42",
      "_origin": "ast",
      "id": "timeline_page_timeline",
      "community": 8,
      "norm_label": "timeline()"
    },
    {
      "label": "Navigation.tsx",
      "file_type": "code",
      "source_file": "src/components/layout/Navigation.tsx",
      "source_location": "L1",
      "_origin": "ast",
      "id": "layout_navigation",
      "community": 1,
      "norm_label": "navigation.tsx"
    },
    {
      "label": "links",
      "file_type": "code",
      "source_file": "src/components/layout/Navigation.tsx",
      "source_location": "L9",
      "_origin": "ast",
      "id": "layout_navigation_links",
      "community": 1,
      "norm_label": "links"
    },
    {
      "label": "Navigation()",
      "file_type": "code",
      "source_file": "src/components/layout/Navigation.tsx",
      "source_location": "L19",
      "_origin": "ast",
      "id": "layout_navigation_navigation",
      "community": 1,
      "norm_label": "navigation()"
    },
    {
      "label": "theme-provider.tsx",
      "file_type": "code",
      "source_file": "src/components/theme-provider.tsx",
      "source_location": "L1",
      "_origin": "ast",
      "id": "components_theme_provider",
      "community": 1,
      "norm_label": "theme-provider.tsx"
    },
    {
      "label": "ThemeProvider()",
      "file_type": "code",
      "source_file": "src/components/theme-provider.tsx",
      "source_location": "L6",
      "_origin": "ast",
      "id": "components_theme_provider_themeprovider",
      "community": 1,
      "norm_label": "themeprovider()"
    },
    {
      "label": "CommandPalette.tsx",
      "file_type": "code",
      "source_file": "src/components/ui/CommandPalette.tsx",
      "source_location": "L1",
      "_origin": "ast",
      "id": "ui_commandpalette",
      "community": 0,
      "norm_label": "commandpalette.tsx"
    },
    {
      "label": "CommandPalette()",
      "file_type": "code",
      "source_file": "src/components/ui/CommandPalette.tsx",
      "source_location": "L8",
      "_origin": "ast",
      "id": "ui_commandpalette_commandpalette",
      "community": 0,
      "norm_label": "commandpalette()"
    },
    {
      "label": "TerminalEasterEgg.tsx",
      "file_type": "code",
      "source_file": "src/components/ui/TerminalEasterEgg.tsx",
      "source_location": "L1",
      "_origin": "ast",
      "id": "ui_terminaleasteregg",
      "community": 1,
      "norm_label": "terminaleasteregg.tsx"
    },
    {
      "label": "TerminalEasterEgg()",
      "file_type": "code",
      "source_file": "src/components/ui/TerminalEasterEgg.tsx",
      "source_location": "L8",
      "_origin": "ast",
      "id": "ui_terminaleasteregg_terminaleasteregg",
      "community": 1,
      "norm_label": "terminaleasteregg()"
    },
    {
      "label": "ThemeToggle.tsx",
      "file_type": "code",
      "source_file": "src/components/ui/ThemeToggle.tsx",
      "source_location": "L1",
      "_origin": "ast",
      "id": "ui_themetoggle",
      "community": 16,
      "norm_label": "themetoggle.tsx"
    },
    {
      "label": "ThemeToggle()",
      "file_type": "code",
      "source_file": "src/components/ui/ThemeToggle.tsx",
      "source_location": "L8",
      "_origin": "ast",
      "id": "ui_themetoggle_themetoggle",
      "community": 16,
      "norm_label": "themetoggle()"
    },
    {
      "label": "button.tsx",
      "file_type": "code",
      "source_file": "src/components/ui/button.tsx",
      "source_location": "L1",
      "_origin": "ast",
      "id": "ui_button",
      "community": 3,
      "norm_label": "button.tsx"
    },
    {
      "label": "buttonVariants",
      "file_type": "code",
      "source_file": "src/components/ui/button.tsx",
      "source_location": "L6",
      "_origin": "ast",
      "id": "ui_button_buttonvariants",
      "community": 3,
      "norm_label": "buttonvariants"
    },
    {
      "label": "Button()",
      "file_type": "code",
      "source_file": "src/components/ui/button.tsx",
      "source_location": "L43",
      "_origin": "ast",
      "id": "ui_button_button",
      "community": 3,
      "norm_label": "button()"
    },
    {
      "label": "MinimalBackground.tsx",
      "file_type": "code",
      "source_file": "src/components/visuals/MinimalBackground.tsx",
      "source_location": "L1",
      "_origin": "ast",
      "id": "visuals_minimalbackground",
      "community": 1,
      "norm_label": "minimalbackground.tsx"
    },
    {
      "label": "SHAPES",
      "file_type": "code",
      "source_file": "src/components/visuals/MinimalBackground.tsx",
      "source_location": "L6",
      "_origin": "ast",
      "id": "visuals_minimalbackground_shapes",
      "community": 1,
      "norm_label": "shapes"
    },
    {
      "label": "Tetromino",
      "file_type": "code",
      "source_file": "src/components/visuals/MinimalBackground.tsx",
      "source_location": "L16",
      "_origin": "ast",
      "id": "visuals_minimalbackground_tetromino",
      "community": 1,
      "norm_label": "tetromino"
    },
    {
      "label": "COLORS",
      "file_type": "code",
      "source_file": "src/components/visuals/MinimalBackground.tsx",
      "source_location": "L24",
      "_origin": "ast",
      "id": "visuals_minimalbackground_colors",
      "community": 1,
      "norm_label": "colors"
    },
    {
      "label": "MinimalBackground()",
      "file_type": "code",
      "source_file": "src/components/visuals/MinimalBackground.tsx",
      "source_location": "L34",
      "_origin": "ast",
      "id": "visuals_minimalbackground_minimalbackground",
      "community": 1,
      "norm_label": "minimalbackground()"
    },
    {
      "label": "NeuralNodes.tsx",
      "file_type": "code",
      "source_file": "src/components/visuals/NeuralNodes.tsx",
      "source_location": "L1",
      "_origin": "ast",
      "id": "visuals_neuralnodes",
      "community": 5,
      "norm_label": "neuralnodes.tsx"
    },
    {
      "label": "NeuralNodes()",
      "file_type": "code",
      "source_file": "src/components/visuals/NeuralNodes.tsx",
      "source_location": "L5",
      "_origin": "ast",
      "id": "visuals_neuralnodes_neuralnodes",
      "community": 5,
      "norm_label": "neuralnodes()"
    },
    {
      "label": "NeuralParticles.tsx",
      "file_type": "code",
      "source_file": "src/components/visuals/NeuralParticles.tsx",
      "source_location": "L1",
      "_origin": "ast",
      "id": "visuals_neuralparticles",
      "community": 2,
      "norm_label": "neuralparticles.tsx"
    },
    {
      "label": "Particle",
      "file_type": "code",
      "source_file": "src/components/visuals/NeuralParticles.tsx",
      "source_location": "L6",
      "_origin": "ast",
      "id": "visuals_neuralparticles_particle",
      "community": 2,
      "norm_label": "particle"
    },
    {
      "label": ".constructor()",
      "file_type": "code",
      "source_file": "src/components/visuals/NeuralParticles.tsx",
      "source_location": "L17",
      "_origin": "ast",
      "id": "visuals_neuralparticles_particle_constructor",
      "community": 2,
      "norm_label": ".constructor()"
    },
    {
      "label": ".update()",
      "file_type": "code",
      "source_file": "src/components/visuals/NeuralParticles.tsx",
      "source_location": "L29",
      "_origin": "ast",
      "id": "visuals_neuralparticles_particle_update",
      "community": 2,
      "norm_label": ".update()"
    },
    {
      "label": ".draw()",
      "file_type": "code",
      "source_file": "src/components/visuals/NeuralParticles.tsx",
      "source_location": "L71",
      "_origin": "ast",
      "id": "visuals_neuralparticles_particle_draw",
      "community": 2,
      "norm_label": ".draw()"
    },
    {
      "label": "NeuralParticles()",
      "file_type": "code",
      "source_file": "src/components/visuals/NeuralParticles.tsx",
      "source_location": "L80",
      "_origin": "ast",
      "id": "visuals_neuralparticles_neuralparticles",
      "community": 2,
      "norm_label": "neuralparticles()"
    },
    {
      "label": "ProjectGalaxy.tsx",
      "file_type": "code",
      "source_file": "src/components/visuals/ProjectGalaxy.tsx",
      "source_location": "L1",
      "_origin": "ast",
      "id": "visuals_projectgalaxy",
      "community": 0,
      "norm_label": "projectgalaxy.tsx"
    },
    {
      "label": "ProjectGalaxy()",
      "file_type": "code",
      "source_file": "src/components/visuals/ProjectGalaxy.tsx",
      "source_location": "L8",
      "_origin": "ast",
      "id": "visuals_projectgalaxy_projectgalaxy",
      "community": 0,
      "norm_label": "projectgalaxy()"
    },
    {
      "label": "projects.ts",
      "file_type": "code",
      "source_file": "src/data/projects.ts",
      "source_location": "L1",
      "_origin": "ast",
      "id": "data_projects",
      "community": 0,
      "norm_label": "projects.ts"
    },
    {
      "label": "LabContentBlock",
      "file_type": "code",
      "source_file": "src/data/projects.ts",
      "source_location": "L1",
      "_origin": "ast",
      "id": "data_projects_labcontentblock",
      "community": 0,
      "norm_label": "labcontentblock"
    },
    {
      "label": "Project",
      "file_type": "code",
      "source_file": "src/data/projects.ts",
      "source_location": "L7",
      "_origin": "ast",
      "id": "data_projects_project",
      "community": 0,
      "norm_label": "project"
    },
    {
      "label": "projects",
      "file_type": "code",
      "source_file": "src/data/projects.ts",
      "source_location": "L44",
      "_origin": "ast",
      "id": "data_projects_projects",
      "community": 0,
      "norm_label": "projects"
    },
    {
      "label": "connections",
      "file_type": "code",
      "source_file": "src/data/projects.ts",
      "source_location": "L966",
      "_origin": "ast",
      "id": "data_projects_connections",
      "community": 0,
      "norm_label": "connections"
    },
    {
      "label": "utils.ts",
      "file_type": "code",
      "source_file": "src/lib/utils.ts",
      "source_location": "L1",
      "_origin": "ast",
      "id": "lib_utils",
      "community": 3,
      "norm_label": "utils.ts"
    },
    {
      "label": "cn()",
      "file_type": "code",
      "source_file": "src/lib/utils.ts",
      "source_location": "L4",
      "_origin": "ast",
      "id": "lib_utils_cn",
      "community": 3,
      "norm_label": "cn()"
    }
  ],
  "links": [
    {
      "relation": "contains",
      "confidence": "EXTRACTED",
      "source_file": "eslint.config.mjs",
      "source_location": "L5",
      "weight": 1.0,
      "confidence_score": 1.0,
      "source": "eslint_config",
      "target": "eslint_config_eslintconfig"
    },
    {
      "relation": "contains",
      "confidence": "EXTRACTED",
      "source_file": "jules_automator.py",
      "source_location": "L64",
      "weight": 1.0,
      "source": "jules_automator",
      "target": "jules_automator_get_page_text",
      "confidence_score": 1.0
    },
    {
      "relation": "contains",
      "confidence": "EXTRACTED",
      "source_file": "jules_automator.py",
      "source_location": "L32",
      "weight": 1.0,
      "source": "jules_automator",
      "target": "jules_automator_run_applescript",
      "confidence_score": 1.0
    },
    {
      "relation": "calls",
      "context": "call",
      "confidence": "EXTRACTED",
      "source_file": "jules_automator.py",
      "source_location": "L68",
      "weight": 1.0,
      "source": "jules_automator_get_page_text",
      "target": "jules_automator_run_applescript",
      "confidence_score": 1.0
    },
    {
      "relation": "contains",
      "confidence": "EXTRACTED",
      "source_file": "next.config.ts",
      "source_location": "L3",
      "weight": 1.0,
      "confidence_score": 1.0,
      "source": "next_config",
      "target": "next_config_nextconfig"
    },
    {
      "relation": "contains",
      "confidence": "EXTRACTED",
      "source_file": "postcss.config.mjs",
      "source_location": "L1",
      "weight": 1.0,
      "confidence_score": 1.0,
      "source": "postcss_config",
      "target": "postcss_config_config"
    },
    {
      "relation": "contains",
      "confidence": "EXTRACTED",
      "source_file": "src/app/about/page.tsx",
      "source_location": "L53",
      "weight": 1.0,
      "confidence_score": 1.0,
      "source": "about_page",
      "target": "about_page_about"
    },
    {
      "relation": "contains",
      "confidence": "EXTRACTED",
      "source_file": "src/app/about/page.tsx",
      "source_location": "L6",
      "weight": 1.0,
      "confidence_score": 1.0,
      "source": "about_page",
      "target": "about_page_pixiedust"
    },
    {
      "relation": "contains",
      "confidence": "EXTRACTED",
      "source_file": "src/app/contact/page.tsx",
      "source_location": "L20",
      "weight": 1.0,
      "confidence_score": 1.0,
      "source": "contact_page",
      "target": "contact_page_contact"
    },
    {
      "relation": "contains",
      "confidence": "EXTRACTED",
      "source_file": "src/app/contact/page.tsx",
      "source_location": "L5",
      "weight": 1.0,
      "confidence_score": 1.0,
      "source": "contact_page",
      "target": "contact_page_githubicon"
    },
    {
      "relation": "contains",
      "confidence": "EXTRACTED",
      "source_file": "src/app/contact/page.tsx",
      "source_location": "L12",
      "weight": 1.0,
      "confidence_score": 1.0,
      "source": "contact_page",
      "target": "contact_page_linkedinicon"
    },
    {
      "relation": "contains",
      "confidence": "EXTRACTED",
      "source_file": "src/app/hobbies/page.tsx",
      "source_location": "L8",
      "weight": 1.0,
      "confidence_score": 1.0,
      "source": "hobbies_page",
      "target": "hobbies_page_hobbies"
    },
    {
      "relation": "contains",
      "confidence": "EXTRACTED",
      "source_file": "src/app/hobbies/page.tsx",
      "source_location": "L29",
      "weight": 1.0,
      "confidence_score": 1.0,
      "source": "hobbies_page",
      "target": "hobbies_page_hobbiespage"
    },
    {
      "relation": "contains",
      "confidence": "EXTRACTED",
      "source_file": "src/app/hobbies/photography/page.tsx",
      "source_location": "L25",
      "weight": 1.0,
      "confidence_score": 1.0,
      "source": "photography_page",
      "target": "photography_page_photographygallery"
    },
    {
      "relation": "contains",
      "confidence": "EXTRACTED",
      "source_file": "src/app/hobbies/photography/page.tsx",
      "source_location": "L9",
      "weight": 1.0,
      "confidence_score": 1.0,
      "source": "photography_page",
      "target": "photography_page_photos"
    },
    {
      "relation": "contains",
      "confidence": "EXTRACTED",
      "source_file": "src/app/hobbies/photography/page.tsx",
      "source_location": "L86",
      "weight": 1.0,
      "confidence_score": 1.0,
      "source": "photography_page",
      "target": "photography_page_photosection"
    },
    {
      "relation": "imports_from",
      "context": "import",
      "confidence": "EXTRACTED",
      "source_file": "src/app/lab/[slug]/page.tsx",
      "source_location": "L7",
      "weight": 1.0,
      "confidence_score": 1.0,
      "source": "src_app_lab_slug_page_tsx_slug_page",
      "target": "data_projects"
    },
    {
      "relation": "imports",
      "context": "import",
      "confidence": "EXTRACTED",
      "source_file": "src/app/lab/[slug]/page.tsx",
      "source_location": "L7",
      "weight": 1.0,
      "confidence_score": 1.0,
      "source": "src_app_lab_slug_page_tsx_slug_page",
      "target": "data_projects_projects"
    },
    {
      "relation": "contains",
      "confidence": "EXTRACTED",
      "source_file": "src/app/lab/[slug]/page.tsx",
      "source_location": "L10",
      "weight": 1.0,
      "confidence_score": 1.0,
      "source": "src_app_lab_slug_page_tsx_slug_page",
      "target": "slug_page_experiencepage"
    },
    {
      "relation": "imports_from",
      "context": "import",
      "confidence": "EXTRACTED",
      "source_file": "src/app/lab/page.tsx",
      "source_location": "L5",
      "weight": 1.0,
      "confidence_score": 1.0,
      "source": "lab_page",
      "target": "data_projects"
    },
    {
      "relation": "imports",
      "context": "import",
      "confidence": "EXTRACTED",
      "source_file": "src/app/lab/page.tsx",
      "source_location": "L5",
      "weight": 1.0,
      "confidence_score": 1.0,
      "source": "lab_page",
      "target": "data_projects_projects"
    },
    {
      "relation": "contains",
      "confidence": "EXTRACTED",
      "source_file": "src/app/lab/page.tsx",
      "source_location": "L8",
      "weight": 1.0,
      "confidence_score": 1.0,
      "source": "lab_page",
      "target": "lab_page_labpage"
    },
    {
      "relation": "contains",
      "confidence": "EXTRACTED",
      "source_file": "src/app/layout.tsx",
      "source_location": "L8",
      "weight": 1.0,
      "confidence_score": 1.0,
      "source": "app_layout",
      "target": "app_layout_metadata"
    },
    {
      "relation": "contains",
      "confidence": "EXTRACTED",
      "source_file": "src/app/layout.tsx",
      "source_location": "L26",
      "weight": 1.0,
      "confidence_score": 1.0,
      "source": "app_layout",
      "target": "app_layout_rootlayout"
    },
    {
      "relation": "imports_from",
      "context": "import",
      "confidence": "EXTRACTED",
      "source_file": "src/app/layout.tsx",
      "source_location": "L4",
      "weight": 1.0,
      "confidence_score": 1.0,
      "source": "app_layout",
      "target": "components_theme_provider"
    },
    {
      "relation": "imports",
      "context": "import",
      "confidence": "EXTRACTED",
      "source_file": "src/app/layout.tsx",
      "source_location": "L4",
      "weight": 1.0,
      "confidence_score": 1.0,
      "source": "app_layout",
      "target": "components_theme_provider_themeprovider"
    },
    {
      "relation": "imports_from",
      "context": "import",
      "confidence": "EXTRACTED",
      "source_file": "src/app/layout.tsx",
      "source_location": "L2",
      "weight": 1.0,
      "confidence_score": 1.0,
      "source": "app_layout",
      "target": "layout_navigation"
    },
    {
      "relation": "imports",
      "context": "import",
      "confidence": "EXTRACTED",
      "source_file": "src/app/layout.tsx",
      "source_location": "L2",
      "weight": 1.0,
      "confidence_score": 1.0,
      "source": "app_layout",
      "target": "layout_navigation_navigation"
    },
    {
      "relation": "imports_from",
      "context": "import",
      "confidence": "EXTRACTED",
      "source_file": "src/app/layout.tsx",
      "source_location": "L3",
      "weight": 1.0,
      "confidence_score": 1.0,
      "source": "app_layout",
      "target": "ui_commandpalette"
    },
    {
      "relation": "imports_from",
      "context": "import",
      "confidence": "EXTRACTED",
      "source_file": "src/app/layout.tsx",
      "source_location": "L4",
      "weight": 1.0,
      "confidence_score": 1.0,
      "source": "app_layout",
      "target": "ui_terminaleasteregg"
    },
    {
      "relation": "imports_from",
      "context": "import",
      "confidence": "EXTRACTED",
      "source_file": "src/app/layout.tsx",
      "source_location": "L1",
      "weight": 1.0,
      "confidence_score": 1.0,
      "source": "app_layout",
      "target": "visuals_minimalbackground"
    },
    {
      "relation": "contains",
      "confidence": "EXTRACTED",
      "source_file": "src/app/now/page.tsx",
      "source_location": "L1",
      "weight": 1.0,
      "confidence_score": 1.0,
      "source": "now_page",
      "target": "now_page_now"
    },
    {
      "relation": "contains",
      "confidence": "EXTRACTED",
      "source_file": "src/app/page.tsx",
      "source_location": "L9",
      "weight": 1.0,
      "confidence_score": 1.0,
      "source": "app_page",
      "target": "app_page_home"
    },
    {
      "relation": "imports_from",
      "context": "import",
      "confidence": "EXTRACTED",
      "source_file": "src/app/page.tsx",
      "source_location": "L7",
      "weight": 1.0,
      "confidence_score": 1.0,
      "source": "app_page",
      "target": "visuals_neuralnodes"
    },
    {
      "relation": "imports_from",
      "context": "import",
      "confidence": "EXTRACTED",
      "source_file": "src/app/project/[slug]/page.tsx",
      "source_location": "L5",
      "weight": 1.0,
      "confidence_score": 1.0,
      "source": "src_app_project_slug_page_tsx_slug_page",
      "target": "data_projects"
    },
    {
      "relation": "imports",
      "context": "import",
      "confidence": "EXTRACTED",
      "source_file": "src/app/project/[slug]/page.tsx",
      "source_location": "L5",
      "weight": 1.0,
      "confidence_score": 1.0,
      "source": "src_app_project_slug_page_tsx_slug_page",
      "target": "data_projects_project"
    },
    {
      "relation": "imports",
      "context": "import",
      "confidence": "EXTRACTED",
      "source_file": "src/app/project/[slug]/page.tsx",
      "source_location": "L5",
      "weight": 1.0,
      "confidence_score": 1.0,
      "source": "src_app_project_slug_page_tsx_slug_page",
      "target": "data_projects_projects"
    },
    {
      "relation": "contains",
      "confidence": "EXTRACTED",
      "source_file": "src/app/project/[slug]/page.tsx",
      "source_location": "L12",
      "weight": 1.0,
      "confidence_score": 1.0,
      "source": "src_app_project_slug_page_tsx_slug_page",
      "target": "slug_page_gettheme"
    },
    {
      "relation": "contains",
      "confidence": "EXTRACTED",
      "source_file": "src/app/project/[slug]/page.tsx",
      "source_location": "L23",
      "weight": 1.0,
      "confidence_score": 1.0,
      "source": "src_app_project_slug_page_tsx_slug_page",
      "target": "slug_page_projectpage"
    },
    {
      "relation": "calls",
      "context": "call",
      "confidence": "EXTRACTED",
      "source_file": "src/app/project/[slug]/page.tsx",
      "source_location": "L51",
      "weight": 1.0,
      "confidence_score": 1.0,
      "source": "slug_page_projectpage",
      "target": "slug_page_gettheme"
    },
    {
      "relation": "imports_from",
      "context": "import",
      "confidence": "EXTRACTED",
      "source_file": "src/app/projects/page.tsx",
      "source_location": "L4",
      "weight": 1.0,
      "confidence_score": 1.0,
      "source": "projects_page",
      "target": "data_projects"
    },
    {
      "relation": "imports",
      "context": "import",
      "confidence": "EXTRACTED",
      "source_file": "src/app/projects/page.tsx",
      "source_location": "L4",
      "weight": 1.0,
      "confidence_score": 1.0,
      "source": "projects_page",
      "target": "data_projects_project"
    },
    {
      "relation": "imports",
      "context": "import",
      "confidence": "EXTRACTED",
      "source_file": "src/app/projects/page.tsx",
      "source_location": "L4",
      "weight": 1.0,
      "confidence_score": 1.0,
      "source": "projects_page",
      "target": "data_projects_projects"
    },
    {
      "relation": "contains",
      "confidence": "EXTRACTED",
      "source_file": "src/app/projects/page.tsx",
      "source_location": "L9",
      "weight": 1.0,
      "confidence_score": 1.0,
      "source": "projects_page",
      "target": "projects_page_allcategories"
    },
    {
      "relation": "contains",
      "confidence": "EXTRACTED",
      "source_file": "src/app/projects/page.tsx",
      "source_location": "L11",
      "weight": 1.0,
      "confidence_score": 1.0,
      "source": "projects_page",
      "target": "projects_page_gettheme"
    },
    {
      "relation": "contains",
      "confidence": "EXTRACTED",
      "source_file": "src/app/projects/page.tsx",
      "source_location": "L18",
      "weight": 1.0,
      "confidence_score": 1.0,
      "source": "projects_page",
      "target": "projects_page_projectcard"
    },
    {
      "relation": "contains",
      "confidence": "EXTRACTED",
      "source_file": "src/app/projects/page.tsx",
      "source_location": "L49",
      "weight": 1.0,
      "confidence_score": 1.0,
      "source": "projects_page",
      "target": "projects_page_projects"
    },
    {
      "relation": "calls",
      "context": "call",
      "confidence": "EXTRACTED",
      "source_file": "src/app/projects/page.tsx",
      "source_location": "L19",
      "weight": 1.0,
      "confidence_score": 1.0,
      "source": "projects_page_projectcard",
      "target": "projects_page_gettheme"
    },
    {
      "relation": "contains",
      "confidence": "EXTRACTED",
      "source_file": "src/app/skills/page.tsx",
      "source_location": "L6",
      "weight": 1.0,
      "confidence_score": 1.0,
      "source": "skills_page",
      "target": "skills_page_skillcategories"
    },
    {
      "relation": "contains",
      "confidence": "EXTRACTED",
      "source_file": "src/app/skills/page.tsx",
      "source_location": "L25",
      "weight": 1.0,
      "confidence_score": 1.0,
      "source": "skills_page",
      "target": "skills_page_skills"
    },
    {
      "relation": "contains",
      "confidence": "EXTRACTED",
      "source_file": "src/app/timeline/page.tsx",
      "source_location": "L35",
      "weight": 1.0,
      "confidence_score": 1.0,
      "source": "timeline_page",
      "target": "timeline_page_gettheme"
    },
    {
      "relation": "contains",
      "confidence": "EXTRACTED",
      "source_file": "src/app/timeline/page.tsx",
      "source_location": "L42",
      "weight": 1.0,
      "confidence_score": 1.0,
      "source": "timeline_page",
      "target": "timeline_page_timeline"
    },
    {
      "relation": "contains",
      "confidence": "EXTRACTED",
      "source_file": "src/app/timeline/page.tsx",
      "source_location": "L6",
      "weight": 1.0,
      "confidence_score": 1.0,
      "source": "timeline_page",
      "target": "timeline_page_timelineevents"
    },
    {
      "relation": "contains",
      "confidence": "EXTRACTED",
      "source_file": "src/components/layout/Navigation.tsx",
      "source_location": "L8",
      "weight": 1.0,
      "confidence_score": 1.0,
      "source": "layout_navigation",
      "target": "layout_navigation_links"
    },
    {
      "relation": "contains",
      "confidence": "EXTRACTED",
      "source_file": "src/components/layout/Navigation.tsx",
      "source_location": "L16",
      "weight": 1.0,
      "confidence_score": 1.0,
      "source": "layout_navigation",
      "target": "layout_navigation_navigation"
    },
    {
      "relation": "contains",
      "confidence": "EXTRACTED",
      "source_file": "src/components/theme-provider.tsx",
      "source_location": "L6",
      "weight": 1.0,
      "confidence_score": 1.0,
      "source": "components_theme_provider",
      "target": "components_theme_provider_themeprovider"
    },
    {
      "relation": "imports_from",
      "context": "import",
      "confidence": "EXTRACTED",
      "source_file": "src/components/ui/CommandPalette.tsx",
      "source_location": "L6",
      "weight": 1.0,
      "confidence_score": 1.0,
      "source": "ui_commandpalette",
      "target": "data_projects"
    },
    {
      "relation": "imports",
      "context": "import",
      "confidence": "EXTRACTED",
      "source_file": "src/components/ui/CommandPalette.tsx",
      "source_location": "L6",
      "weight": 1.0,
      "confidence_score": 1.0,
      "source": "ui_commandpalette",
      "target": "data_projects_projects"
    },
    {
      "relation": "contains",
      "confidence": "EXTRACTED",
      "source_file": "src/components/ui/CommandPalette.tsx",
      "source_location": "L8",
      "weight": 1.0,
      "confidence_score": 1.0,
      "source": "ui_commandpalette",
      "target": "ui_commandpalette_commandpalette"
    },
    {
      "relation": "contains",
      "confidence": "EXTRACTED",
      "source_file": "src/components/ui/TerminalEasterEgg.tsx",
      "source_location": "L8",
      "weight": 1.0,
      "confidence_score": 1.0,
      "source": "ui_terminaleasteregg",
      "target": "ui_terminaleasteregg_terminaleasteregg"
    },
    {
      "relation": "contains",
      "confidence": "EXTRACTED",
      "source_file": "src/components/ui/ThemeToggle.tsx",
      "source_location": "L8",
      "weight": 1.0,
      "confidence_score": 1.0,
      "source": "ui_themetoggle",
      "target": "ui_themetoggle_themetoggle"
    },
    {
      "relation": "imports_from",
      "context": "import",
      "confidence": "EXTRACTED",
      "source_file": "src/components/ui/button.tsx",
      "source_location": "L4",
      "weight": 1.0,
      "confidence_score": 1.0,
      "source": "ui_button",
      "target": "lib_utils"
    },
    {
      "relation": "imports",
      "context": "import",
      "confidence": "EXTRACTED",
      "source_file": "src/components/ui/button.tsx",
      "source_location": "L4",
      "weight": 1.0,
      "confidence_score": 1.0,
      "source": "ui_button",
      "target": "lib_utils_cn"
    },
    {
      "relation": "contains",
      "confidence": "EXTRACTED",
      "source_file": "src/components/ui/button.tsx",
      "source_location": "L43",
      "weight": 1.0,
      "confidence_score": 1.0,
      "source": "ui_button",
      "target": "ui_button_button"
    },
    {
      "relation": "contains",
      "confidence": "EXTRACTED",
      "source_file": "src/components/ui/button.tsx",
      "source_location": "L6",
      "weight": 1.0,
      "confidence_score": 1.0,
      "source": "ui_button",
      "target": "ui_button_buttonvariants"
    },
    {
      "relation": "calls",
      "context": "call",
      "confidence": "EXTRACTED",
      "source_file": "src/components/ui/button.tsx",
      "source_location": "L52",
      "weight": 1.0,
      "confidence_score": 1.0,
      "source": "ui_button_button",
      "target": "ui_button_buttonvariants"
    },
    {
      "relation": "calls",
      "context": "call",
      "confidence": "EXTRACTED",
      "confidence_score": 1.0,
      "source_file": "src/components/ui/button.tsx",
      "source_location": "L52",
      "weight": 1.0,
      "source": "ui_button_button",
      "target": "lib_utils_cn"
    },
    {
      "relation": "contains",
      "confidence": "EXTRACTED",
      "source_file": "src/components/visuals/MinimalBackground.tsx",
      "source_location": "L24",
      "weight": 1.0,
      "confidence_score": 1.0,
      "source": "visuals_minimalbackground",
      "target": "visuals_minimalbackground_colors"
    },
    {
      "relation": "contains",
      "confidence": "EXTRACTED",
      "source_file": "src/components/visuals/MinimalBackground.tsx",
      "source_location": "L34",
      "weight": 1.0,
      "confidence_score": 1.0,
      "source": "visuals_minimalbackground",
      "target": "visuals_minimalbackground_minimalbackground"
    },
    {
      "relation": "contains",
      "confidence": "EXTRACTED",
      "source_file": "src/components/visuals/MinimalBackground.tsx",
      "source_location": "L6",
      "weight": 1.0,
      "confidence_score": 1.0,
      "source": "visuals_minimalbackground",
      "target": "visuals_minimalbackground_shapes"
    },
    {
      "relation": "contains",
      "confidence": "EXTRACTED",
      "source_file": "src/components/visuals/MinimalBackground.tsx",
      "source_location": "L16",
      "weight": 1.0,
      "confidence_score": 1.0,
      "source": "visuals_minimalbackground",
      "target": "visuals_minimalbackground_tetromino"
    },
    {
      "relation": "contains",
      "confidence": "EXTRACTED",
      "source_file": "src/components/visuals/NeuralNodes.tsx",
      "source_location": "L5",
      "weight": 1.0,
      "confidence_score": 1.0,
      "source": "visuals_neuralnodes",
      "target": "visuals_neuralnodes_neuralnodes"
    },
    {
      "relation": "contains",
      "confidence": "EXTRACTED",
      "source_file": "src/components/visuals/NeuralParticles.tsx",
      "source_location": "L80",
      "weight": 1.0,
      "confidence_score": 1.0,
      "source": "visuals_neuralparticles",
      "target": "visuals_neuralparticles_neuralparticles"
    },
    {
      "relation": "contains",
      "confidence": "EXTRACTED",
      "source_file": "src/components/visuals/NeuralParticles.tsx",
      "source_location": "L6",
      "weight": 1.0,
      "confidence_score": 1.0,
      "source": "visuals_neuralparticles",
      "target": "visuals_neuralparticles_particle"
    },
    {
      "relation": "method",
      "confidence": "EXTRACTED",
      "source_file": "src/components/visuals/NeuralParticles.tsx",
      "source_location": "L17",
      "weight": 1.0,
      "confidence_score": 1.0,
      "source": "visuals_neuralparticles_particle",
      "target": "visuals_neuralparticles_particle_constructor"
    },
    {
      "relation": "method",
      "confidence": "EXTRACTED",
      "source_file": "src/components/visuals/NeuralParticles.tsx",
      "source_location": "L71",
      "weight": 1.0,
      "confidence_score": 1.0,
      "source": "visuals_neuralparticles_particle",
      "target": "visuals_neuralparticles_particle_draw"
    },
    {
      "relation": "method",
      "confidence": "EXTRACTED",
      "source_file": "src/components/visuals/NeuralParticles.tsx",
      "source_location": "L29",
      "weight": 1.0,
      "confidence_score": 1.0,
      "source": "visuals_neuralparticles_particle",
      "target": "visuals_neuralparticles_particle_update"
    },
    {
      "relation": "imports_from",
      "context": "import",
      "confidence": "EXTRACTED",
      "source_file": "src/components/visuals/ProjectGalaxy.tsx",
      "source_location": "L6",
      "weight": 1.0,
      "confidence_score": 1.0,
      "source": "visuals_projectgalaxy",
      "target": "data_projects"
    },
    {
      "relation": "imports",
      "context": "import",
      "confidence": "EXTRACTED",
      "source_file": "src/components/visuals/ProjectGalaxy.tsx",
      "source_location": "L6",
      "weight": 1.0,
      "confidence_score": 1.0,
      "source": "visuals_projectgalaxy",
      "target": "data_projects_connections"
    },
    {
      "relation": "imports",
      "context": "import",
      "confidence": "EXTRACTED",
      "source_file": "src/components/visuals/ProjectGalaxy.tsx",
      "source_location": "L6",
      "weight": 1.0,
      "confidence_score": 1.0,
      "source": "visuals_projectgalaxy",
      "target": "data_projects_projects"
    },
    {
      "relation": "contains",
      "confidence": "EXTRACTED",
      "source_file": "src/components/visuals/ProjectGalaxy.tsx",
      "source_location": "L8",
      "weight": 1.0,
      "confidence_score": 1.0,
      "source": "visuals_projectgalaxy",
      "target": "visuals_projectgalaxy_projectgalaxy"
    },
    {
      "relation": "contains",
      "confidence": "EXTRACTED",
      "source_file": "src/data/projects.ts",
      "source_location": "L605",
      "weight": 1.0,
      "confidence_score": 1.0,
      "source": "data_projects",
      "target": "data_projects_connections"
    },
    {
      "relation": "contains",
      "confidence": "EXTRACTED",
      "source_file": "src/data/projects.ts",
      "source_location": "L1",
      "weight": 1.0,
      "confidence_score": 1.0,
      "source": "data_projects",
      "target": "data_projects_labcontentblock"
    },
    {
      "relation": "contains",
      "confidence": "EXTRACTED",
      "source_file": "src/data/projects.ts",
      "source_location": "L1",
      "weight": 1.0,
      "confidence_score": 1.0,
      "source": "data_projects",
      "target": "data_projects_project"
    },
    {
      "relation": "contains",
      "confidence": "EXTRACTED",
      "source_file": "src/data/projects.ts",
      "source_location": "L35",
      "weight": 1.0,
      "confidence_score": 1.0,
      "source": "data_projects",
      "target": "data_projects_projects"
    },
    {
      "relation": "contains",
      "confidence": "EXTRACTED",
      "source_file": "src/lib/utils.ts",
      "source_location": "L4",
      "weight": 1.0,
      "confidence_score": 1.0,
      "source": "lib_utils",
      "target": "lib_utils_cn"
    }
  ],
  "hyperedges": [],
  "built_at_commit": "b4d137eb27f91b22d55a303adef3ed490b3ca461"
}